nampi/__init__.py
nampi/zadachki.py
scypy/__init__.py
scypy/cv2.py
scypy/zadachki.py
scypy-0.0.7.dist-info/METADATA
scypy-0.0.7.dist-info/WHEEL
scypy-0.0.7.dist-info/top_level.txt
scypy-0.0.7.dist-info/RECORD
